jeans/__init__.py
jeans/main.py
jeans/test.py
jeans-1.8.4.dist-info/licenses/LICENSE
jeans-1.8.4.dist-info/METADATA
jeans-1.8.4.dist-info/WHEEL
jeans-1.8.4.dist-info/top_level.txt
jeans-1.8.4.dist-info/RECORD
