Metadata-Version: 2.4
Name: jeans
Version: 1.8.4
Summary: package to compute integrals related to spherical Jeans equation, including various parametric functions to describe halo and tracer components
Author-email: "Matthew G. Walker" <mgwalker@cmu.edu>
Project-URL: Homepage, https://github.com/mgwalkergit/jeans
Project-URL: Issues, https://github.com/mgwalkergit/jeans/issues
Classifier: Programming Language :: Python :: 3
Classifier: License :: OSI Approved :: MIT License
Classifier: Operating System :: OS Independent
Requires-Python: >=3.8
License-File: LICENSE
Requires-Dist: numpy
Requires-Dist: scipy
Requires-Dist: astropy
Requires-Dist: matplotlib
Dynamic: license-file
